unipi_control/__init__.py
unipi_control/config.py
unipi_control/features.py
unipi_control/log.py
unipi_control/modbus.py
unipi_control/neuron.py
unipi_control/unipi_control.py
unipi_control/version.py
unipi_control/extensions/__init__.py
unipi_control/extensions/eastron.py
unipi_control/integrations/__init__.py
unipi_control/integrations/covers.py
unipi_control/mqtt/__init__.py
unipi_control/mqtt/features.py
unipi_control/mqtt/discovery/__init__.py
unipi_control/mqtt/discovery/binary_sensors.py
unipi_control/mqtt/discovery/covers.py
unipi_control/mqtt/discovery/mixin.py
unipi_control/mqtt/discovery/sensors.py
unipi_control/mqtt/discovery/switches.py
unipi_control/mqtt/integrations/__init__.py
unipi_control/mqtt/integrations/covers.py
unipi_control/tools/__init__.py
unipi_control/tools/config_backup.py
unipi_control/tools/config_converter.py
unipi_control/tools/model_info.py
unipi_control-2023.7.dist-info/LICENSE
unipi_control-2023.7.dist-info/METADATA
unipi_control-2023.7.dist-info/WHEEL
unipi_control-2023.7.dist-info/entry_points.txt
unipi_control-2023.7.dist-info/top_level.txt
unipi_control-2023.7.dist-info/RECORD
