Metadata-Version: 2.1
Name: unipi-control
Version: 2023.7
Summary: Control Unipi I/O directly with MQTT commands.
Home-page: https://github.com/superbox-dev/unipi-control
Author: Michael Hacker
Author-email: mh@superbox.one
License: Apache-2.0 license
Project-URL: Source Code, https://github.com/superbox-dev/unipi-control
Project-URL: Bug Reports, https://github.com/superbox-dev/unipi-control/issues
Classifier: Development Status :: 5 - Production/Stable
Classifier: License :: OSI Approved :: Apache Software License
Classifier: Programming Language :: Python :: 3
Classifier: Programming Language :: Python :: 3.8
Classifier: Programming Language :: Python :: 3.9
Classifier: Programming Language :: Python :: 3.10
Classifier: Programming Language :: Python :: 3.11
Classifier: Programming Language :: Python :: 3 :: Only
Classifier: Operating System :: POSIX :: Linux
Classifier: Topic :: System :: Networking
Classifier: Topic :: Utilities
Requires-Python: >=3.8
License-File: LICENSE
Requires-Dist: pymodbus[serial] (==3.2.2)
Requires-Dist: superbox-utils[mqtt] (==2023.6)
